[
  {
    "reservation": [
      {
        "id": "12d60de1-4747-4afc-849b-8f079d4d5405",
        "table_number": 94996,
        "reservation_time": "2023-08-09T15:09:43.111Z",
        "created_at": "2023-08-09T14:31:56.002Z",
        "updated_at": "2023-08-10T06:43:04.943Z",
        "guest_id": "user_entity_pk",
        "restaurant_id": "main_entity_pk"
      },
      {
        "id": "a0b31fc1-3a03-4e24-bf34-b55cc80c7a49",
        "table_number": 28476,
        "reservation_time": "2023-08-10T08:34:56.306Z",
        "created_at": "2023-08-10T06:30:13.296Z",
        "updated_at": "2023-08-10T03:42:36.025Z",
        "guest_id": "user_entity_pk",
        "restaurant_id": "main_entity_pk"
      },
      {
        "id": "fd0da473-56fa-4d7a-8162-024487a6894d",
        "table_number": 45292,
        "reservation_time": "2023-08-09T16:41:26.556Z",
        "created_at": "2023-08-10T04:01:17.656Z",
        "updated_at": "2023-08-09T15:39:13.506Z",
        "guest_id": "user_entity_pk",
        "restaurant_id": "main_entity_pk"
      },
      {
        "id": "c9a17e84-c8e6-46f1-90e9-bc40254c53e2",
        "table_number": 43367,
        "reservation_time": "2023-08-09T15:06:49.622Z",
        "created_at": "2023-08-10T09:02:05.464Z",
        "updated_at": "2023-08-09T16:05:27.435Z",
        "guest_id": "user_entity_pk",
        "restaurant_id": "main_entity_pk"
      },
      {
        "id": "a87557dd-b12e-4072-9df7-eab5b23971bf",
        "table_number": 70695,
        "reservation_time": "2023-08-09T18:52:14.537Z",
        "created_at": "2023-08-10T03:06:46.078Z",
        "updated_at": "2023-08-10T09:05:49.153Z",
        "guest_id": "user_entity_pk",
        "restaurant_id": "main_entity_pk"
      }
    ],
    "menu": [
      {
        "id": "2deaa56d-f6fb-470e-9788-6a4731a30de0",
        "name": "Grilled Salmon",
        "created_at": "2023-08-09T16:13:42.933Z",
        "updated_at": "2023-08-10T10:08:27.706Z",
        "restaurant_id": "main_entity_pk"
      },
      {
        "id": "4611c1dc-c499-4255-ad49-9f02d5a01468",
        "name": "Margherita Pizza",
        "created_at": "2023-08-09T21:59:53.303Z",
        "updated_at": "2023-08-09T17:25:44.723Z",
        "restaurant_id": "main_entity_pk"
      },
      {
        "id": "8248ca0f-651c-4d36-a44d-631de91fe767",
        "name": "Chicken Alfredo Pasta",
        "created_at": "2023-08-09T13:53:25.747Z",
        "updated_at": "2023-08-10T00:32:23.025Z",
        "restaurant_id": "main_entity_pk"
      },
      {
        "id": "3e81341d-1a7c-4ebe-b1d4-7ed21022fe60",
        "name": "Beef Burger",
        "created_at": "2023-08-10T10:07:52.558Z",
        "updated_at": "2023-08-10T01:56:04.213Z",
        "restaurant_id": "main_entity_pk"
      },
      {
        "id": "46da1748-70f8-4cf0-95e5-c5c652b8d176",
        "name": "Vegetable Stir-Fry",
        "created_at": "2023-08-09T21:52:18.783Z",
        "updated_at": "2023-08-09T20:58:46.939Z",
        "restaurant_id": "main_entity_pk"
      }
    ],
    "roqUser": [
      {
        "reference": "bf624fb7-c631-44c9-b89d-9ea2015df9ab",
        "email": "Isabel_Nader22@gmail.com",
        "firstName": "Rusty",
        "lastName": "Marquardt",
        "active": true,
        "avatarUrl": "https://avatars.githubusercontent.com/u/53783415",
        "tenantId": null
      },
      {
        "reference": "7c89eea1-a6e8-48b0-aa90-3ac24d805294",
        "email": "Alvina_Treutel46@hotmail.com",
        "firstName": "Winfield",
        "lastName": "Daugherty",
        "active": true,
        "avatarUrl": "https://avatars.githubusercontent.com/u/87248361",
        "tenantId": null
      },
      {
        "reference": "30765a12-c8b9-4cc9-ba96-42f86e54142a",
        "email": "Nathanael_Hodkiewicz@hotmail.com",
        "firstName": "Kurtis",
        "lastName": "Zemlak",
        "active": true,
        "avatarUrl": "https://cloudflare-ipfs.com/ipfs/Qmd3W5DuhgHirLHGVixi6V76LhCkZUz6pnFt5AJBiyvHye/avatar/601.jpg",
        "tenantId": null
      },
      {
        "reference": "135ad976-817b-4d79-ae41-c4c0136e7e8a",
        "email": "Brice47@yahoo.com",
        "firstName": "Montana",
        "lastName": "Roberts",
        "active": true,
        "avatarUrl": "https://avatars.githubusercontent.com/u/75860657",
        "tenantId": null
      },
      {
        "reference": "c9ea44ad-38b8-4ad0-8b83-310102d587e9",
        "email": "Lexi89@gmail.com",
        "firstName": "Myrtie",
        "lastName": "Lueilwitz",
        "active": true,
        "avatarUrl": "https://cloudflare-ipfs.com/ipfs/Qmd3W5DuhgHirLHGVixi6V76LhCkZUz6pnFt5AJBiyvHye/avatar/98.jpg",
        "tenantId": null
      }
    ]
  },
  {
    "reservation": [
      {
        "id": "da4b2020-b2c0-4ac0-87c1-107c18b2f48f",
        "table_number": 20846,
        "reservation_time": "2023-08-09T21:42:51.381Z",
        "created_at": "2023-08-10T09:42:34.121Z",
        "updated_at": "2023-08-10T11:46:05.062Z",
        "guest_id": "user_entity_pk",
        "restaurant_id": "main_entity_pk"
      },
      {
        "id": "da53f274-e9b8-4b87-aa3c-10a10cf4af2f",
        "table_number": 80267,
        "reservation_time": "2023-08-09T23:31:56.074Z",
        "created_at": "2023-08-10T08:16:33.000Z",
        "updated_at": "2023-08-10T02:09:58.299Z",
        "guest_id": "user_entity_pk",
        "restaurant_id": "main_entity_pk"
      },
      {
        "id": "dec03f8e-be09-4858-a3e3-1709cb905cff",
        "table_number": 64092,
        "reservation_time": "2023-08-10T03:53:40.588Z",
        "created_at": "2023-08-10T09:30:54.007Z",
        "updated_at": "2023-08-10T00:52:55.250Z",
        "guest_id": "user_entity_pk",
        "restaurant_id": "main_entity_pk"
      },
      {
        "id": "0936535f-daae-4d64-960a-b0233321134a",
        "table_number": 50437,
        "reservation_time": "2023-08-10T10:28:56.393Z",
        "created_at": "2023-08-09T12:44:43.500Z",
        "updated_at": "2023-08-09T18:00:27.988Z",
        "guest_id": "user_entity_pk",
        "restaurant_id": "main_entity_pk"
      },
      {
        "id": "92d69918-9dd2-42c6-8c7e-7a2d096ace10",
        "table_number": 3713,
        "reservation_time": "2023-08-09T12:03:14.740Z",
        "created_at": "2023-08-09T22:40:06.912Z",
        "updated_at": "2023-08-09T19:11:12.623Z",
        "guest_id": "user_entity_pk",
        "restaurant_id": "main_entity_pk"
      }
    ],
    "menu": [
      {
        "id": "7bc21a40-789f-40d1-9038-fd8284df103c",
        "name": "Grilled Salmon",
        "created_at": "2023-08-09T17:16:56.763Z",
        "updated_at": "2023-08-10T06:16:55.264Z",
        "restaurant_id": "main_entity_pk"
      },
      {
        "id": "fffa60b5-6b14-40a5-89b7-b4a9a7c061d5",
        "name": "Margherita Pizza",
        "created_at": "2023-08-10T09:15:58.822Z",
        "updated_at": "2023-08-09T17:01:38.054Z",
        "restaurant_id": "main_entity_pk"
      },
      {
        "id": "7621162f-b1cb-42c2-85fa-fec7244304ac",
        "name": "Chicken Alfredo Pasta",
        "created_at": "2023-08-10T02:02:30.117Z",
        "updated_at": "2023-08-10T08:44:43.486Z",
        "restaurant_id": "main_entity_pk"
      },
      {
        "id": "d06be087-7436-43a0-9988-de2419ed403c",
        "name": "Beef Burger",
        "created_at": "2023-08-10T00:20:27.159Z",
        "updated_at": "2023-08-09T14:57:46.762Z",
        "restaurant_id": "main_entity_pk"
      },
      {
        "id": "0954da03-a38f-43fb-a5c4-3a8e98e89969",
        "name": "Vegetable Stir-Fry",
        "created_at": "2023-08-09T21:51:13.812Z",
        "updated_at": "2023-08-09T22:36:54.839Z",
        "restaurant_id": "main_entity_pk"
      }
    ],
    "roqUser": [
      {
        "reference": "51f199ab-a6e5-4d56-964e-41d0ca6a8ad7",
        "email": "Allie.Pagac@gmail.com",
        "firstName": "Rosemarie",
        "lastName": "Hahn",
        "active": true,
        "avatarUrl": "https://cloudflare-ipfs.com/ipfs/Qmd3W5DuhgHirLHGVixi6V76LhCkZUz6pnFt5AJBiyvHye/avatar/1175.jpg",
        "tenantId": null
      },
      {
        "reference": "de8eb28b-6985-4c39-95db-b06d8f8de51a",
        "email": "Beulah6@gmail.com",
        "firstName": "Althea",
        "lastName": "Barton",
        "active": true,
        "avatarUrl": "https://cloudflare-ipfs.com/ipfs/Qmd3W5DuhgHirLHGVixi6V76LhCkZUz6pnFt5AJBiyvHye/avatar/143.jpg",
        "tenantId": null
      },
      {
        "reference": "dd8b3e93-db15-4e80-b33f-99e51f37cb36",
        "email": "Jaclyn_Cummings@yahoo.com",
        "firstName": "Mohammed",
        "lastName": "Doyle",
        "active": true,
        "avatarUrl": "https://avatars.githubusercontent.com/u/65367738",
        "tenantId": null
      },
      {
        "reference": "6f951299-fa61-4bed-b095-fdec26c3fd53",
        "email": "Mallory.Herman@gmail.com",
        "firstName": "Ilene",
        "lastName": "Kuvalis",
        "active": true,
        "avatarUrl": "https://avatars.githubusercontent.com/u/1937871",
        "tenantId": null
      },
      {
        "reference": "17fd504e-00cb-4c23-b5ce-91cab0ff002a",
        "email": "Antwan_Kling79@yahoo.com",
        "firstName": "Lavinia",
        "lastName": "McGlynn",
        "active": true,
        "avatarUrl": "https://avatars.githubusercontent.com/u/46635669",
        "tenantId": null
      }
    ]
  },
  {
    "reservation": [
      {
        "id": "83bafcb1-4934-464d-a2b9-93845c4c8516",
        "table_number": 85166,
        "reservation_time": "2023-08-09T17:18:26.973Z",
        "created_at": "2023-08-09T14:17:57.914Z",
        "updated_at": "2023-08-10T06:48:10.282Z",
        "guest_id": "user_entity_pk",
        "restaurant_id": "main_entity_pk"
      },
      {
        "id": "d021a1c5-181e-40e6-b299-cc599b2914ff",
        "table_number": 24747,
        "reservation_time": "2023-08-10T06:48:01.120Z",
        "created_at": "2023-08-09T18:59:53.530Z",
        "updated_at": "2023-08-09T18:32:51.327Z",
        "guest_id": "user_entity_pk",
        "restaurant_id": "main_entity_pk"
      },
      {
        "id": "5a6fc2bb-fe7b-4ebf-ac7d-6a1884dd2940",
        "table_number": 82777,
        "reservation_time": "2023-08-09T17:25:47.498Z",
        "created_at": "2023-08-10T01:11:06.028Z",
        "updated_at": "2023-08-10T00:05:25.649Z",
        "guest_id": "user_entity_pk",
        "restaurant_id": "main_entity_pk"
      },
      {
        "id": "7a9d28a2-fb7e-493d-9958-b45b8aed6ec9",
        "table_number": 16678,
        "reservation_time": "2023-08-09T22:02:50.547Z",
        "created_at": "2023-08-10T07:24:11.145Z",
        "updated_at": "2023-08-09T17:08:56.214Z",
        "guest_id": "user_entity_pk",
        "restaurant_id": "main_entity_pk"
      },
      {
        "id": "b96c4550-acc7-4009-8cb8-97d35065182e",
        "table_number": 41561,
        "reservation_time": "2023-08-10T09:48:55.050Z",
        "created_at": "2023-08-10T08:57:20.650Z",
        "updated_at": "2023-08-09T17:17:19.753Z",
        "guest_id": "user_entity_pk",
        "restaurant_id": "main_entity_pk"
      }
    ],
    "menu": [
      {
        "id": "0da19965-0987-4650-a25d-11405e50d6bf",
        "name": "Grilled Salmon",
        "created_at": "2023-08-09T19:46:52.108Z",
        "updated_at": "2023-08-10T06:49:48.903Z",
        "restaurant_id": "main_entity_pk"
      },
      {
        "id": "b26daa39-3cf0-40cf-b038-9484e682627f",
        "name": "Margherita Pizza",
        "created_at": "2023-08-09T16:38:11.614Z",
        "updated_at": "2023-08-10T05:52:29.428Z",
        "restaurant_id": "main_entity_pk"
      },
      {
        "id": "948c5c1b-60e4-4b71-8d66-98781336e300",
        "name": "Chicken Alfredo Pasta",
        "created_at": "2023-08-10T09:25:56.349Z",
        "updated_at": "2023-08-10T11:23:51.087Z",
        "restaurant_id": "main_entity_pk"
      },
      {
        "id": "b2516f3b-28f7-4092-a21a-a9ad70c2f374",
        "name": "Beef Burger",
        "created_at": "2023-08-09T23:36:03.461Z",
        "updated_at": "2023-08-10T06:32:13.263Z",
        "restaurant_id": "main_entity_pk"
      },
      {
        "id": "2bf02ede-ff05-4816-b928-3239cddb947d",
        "name": "Vegetable Stir-Fry",
        "created_at": "2023-08-09T15:22:49.341Z",
        "updated_at": "2023-08-09T18:43:23.865Z",
        "restaurant_id": "main_entity_pk"
      }
    ],
    "roqUser": [
      {
        "reference": "88f32fc2-d183-4f02-bd47-4adce2c3a8e5",
        "email": "Loma.Schiller@gmail.com",
        "firstName": "Stephen",
        "lastName": "Marquardt",
        "active": true,
        "avatarUrl": "https://avatars.githubusercontent.com/u/86034789",
        "tenantId": null
      },
      {
        "reference": "3eaad3bd-c938-474a-b895-e88cea155d10",
        "email": "Rossie17@hotmail.com",
        "firstName": "Deshaun",
        "lastName": "Zemlak",
        "active": true,
        "avatarUrl": "https://avatars.githubusercontent.com/u/7086198",
        "tenantId": null
      },
      {
        "reference": "5f9623aa-bce8-48a9-b574-fb04ce2214c4",
        "email": "Bret54@hotmail.com",
        "firstName": "Trudie",
        "lastName": "Goyette",
        "active": true,
        "avatarUrl": "https://cloudflare-ipfs.com/ipfs/Qmd3W5DuhgHirLHGVixi6V76LhCkZUz6pnFt5AJBiyvHye/avatar/333.jpg",
        "tenantId": null
      },
      {
        "reference": "3e4f4a5c-b8aa-4d7e-b2a0-dec365fd8885",
        "email": "Archibald.Stoltenberg@yahoo.com",
        "firstName": "Ernest",
        "lastName": "Pouros",
        "active": true,
        "avatarUrl": "https://avatars.githubusercontent.com/u/42304504",
        "tenantId": null
      },
      {
        "reference": "d0e44ec2-0aa7-46aa-b904-267733b870cc",
        "email": "Elbert_McDermott70@yahoo.com",
        "firstName": "Liza",
        "lastName": "Boyer",
        "active": true,
        "avatarUrl": "https://avatars.githubusercontent.com/u/57564184",
        "tenantId": null
      }
    ]
  },
  {
    "reservation": [
      {
        "id": "215396a0-309a-424c-870a-e8f6b0d313f1",
        "table_number": 2962,
        "reservation_time": "2023-08-09T20:36:53.596Z",
        "created_at": "2023-08-09T21:44:29.081Z",
        "updated_at": "2023-08-09T22:32:14.421Z",
        "guest_id": "user_entity_pk",
        "restaurant_id": "main_entity_pk"
      },
      {
        "id": "b5e90877-e9fc-48da-8c11-4614951e0174",
        "table_number": 35035,
        "reservation_time": "2023-08-10T02:37:11.317Z",
        "created_at": "2023-08-09T23:01:38.273Z",
        "updated_at": "2023-08-09T17:45:41.170Z",
        "guest_id": "user_entity_pk",
        "restaurant_id": "main_entity_pk"
      },
      {
        "id": "75771423-5976-4c64-bd27-1022efc9e713",
        "table_number": 2645,
        "reservation_time": "2023-08-10T07:17:18.571Z",
        "created_at": "2023-08-09T12:02:34.889Z",
        "updated_at": "2023-08-10T01:21:52.467Z",
        "guest_id": "user_entity_pk",
        "restaurant_id": "main_entity_pk"
      },
      {
        "id": "f214fde1-3897-496d-8351-8c296cb4982d",
        "table_number": 20353,
        "reservation_time": "2023-08-10T10:35:41.614Z",
        "created_at": "2023-08-09T13:23:40.301Z",
        "updated_at": "2023-08-09T14:20:42.180Z",
        "guest_id": "user_entity_pk",
        "restaurant_id": "main_entity_pk"
      },
      {
        "id": "a9c7b8f4-a04e-409d-b2b3-6684286ba80f",
        "table_number": 8990,
        "reservation_time": "2023-08-10T01:56:25.517Z",
        "created_at": "2023-08-10T04:01:16.216Z",
        "updated_at": "2023-08-10T09:26:38.563Z",
        "guest_id": "user_entity_pk",
        "restaurant_id": "main_entity_pk"
      }
    ],
    "menu": [
      {
        "id": "b2c0b8da-48db-4ede-be63-a0708bd795f6",
        "name": "Breakfast Specials",
        "created_at": "2023-08-09T15:45:25.123Z",
        "updated_at": "2023-08-09T20:22:45.852Z",
        "restaurant_id": "main_entity_pk"
      },
      {
        "id": "88dd67fe-c82e-499e-bbbf-01a7e977ca2b",
        "name": "Lunch Combos",
        "created_at": "2023-08-09T18:58:18.499Z",
        "updated_at": "2023-08-10T11:30:39.503Z",
        "restaurant_id": "main_entity_pk"
      },
      {
        "id": "bccfed3f-9b33-44d9-81fd-343b3a151c6c",
        "name": "Dinner Delights",
        "created_at": "2023-08-10T05:38:59.636Z",
        "updated_at": "2023-08-09T20:34:21.330Z",
        "restaurant_id": "main_entity_pk"
      },
      {
        "id": "8d7723d3-d6a5-4266-a65f-081058d3d473",
        "name": "Vegetarian Options",
        "created_at": "2023-08-10T09:40:50.817Z",
        "updated_at": "2023-08-09T14:23:32.083Z",
        "restaurant_id": "main_entity_pk"
      },
      {
        "id": "13fdee97-d918-4436-a002-18995d94b82a",
        "name": "Chef's Recommendations",
        "created_at": "2023-08-10T02:02:36.097Z",
        "updated_at": "2023-08-09T13:03:53.417Z",
        "restaurant_id": "main_entity_pk"
      }
    ],
    "roqUser": [
      {
        "reference": "ad0bb929-a04b-46e3-93e0-0cc4e3c5e005",
        "email": "Junior.Deckow74@hotmail.com",
        "firstName": "Autumn",
        "lastName": "Aufderhar",
        "active": true,
        "avatarUrl": "https://avatars.githubusercontent.com/u/24135422",
        "tenantId": null
      },
      {
        "reference": "5a7903ca-497a-41c8-846e-9adc746d032b",
        "email": "Arne_Armstrong@hotmail.com",
        "firstName": "Lia",
        "lastName": "Bahringer",
        "active": true,
        "avatarUrl": "https://cloudflare-ipfs.com/ipfs/Qmd3W5DuhgHirLHGVixi6V76LhCkZUz6pnFt5AJBiyvHye/avatar/938.jpg",
        "tenantId": null
      },
      {
        "reference": "006f259d-0c48-4aa2-ad0e-ffb808a97e8d",
        "email": "Alessia58@hotmail.com",
        "firstName": "Maegan",
        "lastName": "Nitzsche",
        "active": true,
        "avatarUrl": "https://cloudflare-ipfs.com/ipfs/Qmd3W5DuhgHirLHGVixi6V76LhCkZUz6pnFt5AJBiyvHye/avatar/343.jpg",
        "tenantId": null
      },
      {
        "reference": "7a92be49-c8d8-4266-b83d-a2837c71f8a4",
        "email": "Eda.Legros73@gmail.com",
        "firstName": "Myrtle",
        "lastName": "Wuckert",
        "active": true,
        "avatarUrl": "https://avatars.githubusercontent.com/u/85383180",
        "tenantId": null
      },
      {
        "reference": "6cbfc41a-4d66-45d1-9367-f14e1be69dff",
        "email": "Mittie53@hotmail.com",
        "firstName": "Brant",
        "lastName": "Macejkovic",
        "active": true,
        "avatarUrl": "https://avatars.githubusercontent.com/u/83019675",
        "tenantId": null
      }
    ]
  },
  {
    "reservation": [
      {
        "id": "5fc86e2d-24ba-404d-85a2-dca35cb98b5e",
        "table_number": 89355,
        "reservation_time": "2023-08-10T09:38:14.996Z",
        "created_at": "2023-08-10T01:23:56.402Z",
        "updated_at": "2023-08-09T18:45:48.442Z",
        "guest_id": "user_entity_pk",
        "restaurant_id": "main_entity_pk"
      },
      {
        "id": "8924f34d-5032-4894-b72e-7200cff2f90d",
        "table_number": 74058,
        "reservation_time": "2023-08-10T05:08:12.303Z",
        "created_at": "2023-08-10T05:46:18.130Z",
        "updated_at": "2023-08-10T03:13:16.173Z",
        "guest_id": "user_entity_pk",
        "restaurant_id": "main_entity_pk"
      },
      {
        "id": "6672ddda-ed85-4b0e-bba0-818e94be271c",
        "table_number": 31348,
        "reservation_time": "2023-08-10T04:22:58.068Z",
        "created_at": "2023-08-09T23:31:45.106Z",
        "updated_at": "2023-08-10T08:15:19.099Z",
        "guest_id": "user_entity_pk",
        "restaurant_id": "main_entity_pk"
      },
      {
        "id": "ab1269ce-e266-4654-a3e5-72466a4b40ce",
        "table_number": 19307,
        "reservation_time": "2023-08-10T00:00:39.912Z",
        "created_at": "2023-08-09T23:53:53.898Z",
        "updated_at": "2023-08-10T09:20:39.762Z",
        "guest_id": "user_entity_pk",
        "restaurant_id": "main_entity_pk"
      },
      {
        "id": "981a230f-f092-4878-a9fa-e4401e373179",
        "table_number": 96395,
        "reservation_time": "2023-08-09T21:49:56.400Z",
        "created_at": "2023-08-10T10:45:26.143Z",
        "updated_at": "2023-08-10T03:36:49.719Z",
        "guest_id": "user_entity_pk",
        "restaurant_id": "main_entity_pk"
      }
    ],
    "menu": [
      {
        "id": "d884e760-86b9-4fed-98ad-d06de966be53",
        "name": "Breakfast Specials",
        "created_at": "2023-08-10T11:18:00.864Z",
        "updated_at": "2023-08-09T12:29:13.849Z",
        "restaurant_id": "main_entity_pk"
      },
      {
        "id": "772323ee-530f-4b0f-a485-4e428e33fde3",
        "name": "Lunch Combos",
        "created_at": "2023-08-09T23:09:39.849Z",
        "updated_at": "2023-08-10T00:14:39.098Z",
        "restaurant_id": "main_entity_pk"
      },
      {
        "id": "b63e452f-2731-4589-94e4-1968125f50ee",
        "name": "Dinner Entrees",
        "created_at": "2023-08-10T02:38:16.762Z",
        "updated_at": "2023-08-10T01:04:46.315Z",
        "restaurant_id": "main_entity_pk"
      },
      {
        "id": "bbb1424a-cd54-4d00-82c6-14dacbd31ab6",
        "name": "Vegetarian Options",
        "created_at": "2023-08-10T05:06:24.082Z",
        "updated_at": "2023-08-10T10:08:31.783Z",
        "restaurant_id": "main_entity_pk"
      },
      {
        "id": "c660d219-347e-4afa-8249-55b05fd5fc1b",
        "name": "Dessert Selections",
        "created_at": "2023-08-10T06:36:19.383Z",
        "updated_at": "2023-08-10T08:35:02.273Z",
        "restaurant_id": "main_entity_pk"
      }
    ],
    "roqUser": [
      {
        "reference": "f91ac1cf-a681-47db-aec4-0ca72af01fbc",
        "email": "Letha.Wolf83@hotmail.com",
        "firstName": "Brock",
        "lastName": "Boehm",
        "active": true,
        "avatarUrl": "https://avatars.githubusercontent.com/u/23141371",
        "tenantId": null
      },
      {
        "reference": "01263898-44e2-4c80-ad60-1586247708ff",
        "email": "Norberto_Daugherty@yahoo.com",
        "firstName": "Emery",
        "lastName": "Cremin",
        "active": true,
        "avatarUrl": "https://avatars.githubusercontent.com/u/26573248",
        "tenantId": null
      },
      {
        "reference": "5c42cf6a-9e83-4804-b3a9-fd53b18dd9a7",
        "email": "Adriel.Hackett@hotmail.com",
        "firstName": "Mateo",
        "lastName": "Rath",
        "active": true,
        "avatarUrl": "https://cloudflare-ipfs.com/ipfs/Qmd3W5DuhgHirLHGVixi6V76LhCkZUz6pnFt5AJBiyvHye/avatar/650.jpg",
        "tenantId": null
      },
      {
        "reference": "c9e51c93-ca11-4f59-90b3-559820e2af8f",
        "email": "Elliot14@gmail.com",
        "firstName": "Terrill",
        "lastName": "Zemlak",
        "active": true,
        "avatarUrl": "https://avatars.githubusercontent.com/u/68168629",
        "tenantId": null
      },
      {
        "reference": "9cbfa6f4-64c0-4f5b-8930-d6a7167483f8",
        "email": "Dean81@hotmail.com",
        "firstName": "Natalia",
        "lastName": "Walker",
        "active": true,
        "avatarUrl": "https://avatars.githubusercontent.com/u/46341465",
        "tenantId": null
      }
    ]
  },
  {
    "reservation": [
      {
        "id": "88e9cec0-f290-4729-99e9-00b4f3d43fae",
        "table_number": 65755,
        "reservation_time": "2023-08-09T18:52:36.235Z",
        "created_at": "2023-08-09T13:20:38.799Z",
        "updated_at": "2023-08-10T03:57:22.951Z",
        "guest_id": "user_entity_pk",
        "restaurant_id": "main_entity_pk"
      },
      {
        "id": "633b57a5-1a67-41e3-bed4-4c7e4fe64c04",
        "table_number": 91562,
        "reservation_time": "2023-08-09T12:23:35.125Z",
        "created_at": "2023-08-09T17:33:17.646Z",
        "updated_at": "2023-08-09T12:21:39.557Z",
        "guest_id": "user_entity_pk",
        "restaurant_id": "main_entity_pk"
      },
      {
        "id": "4b4d8b2a-344e-4e3a-bd21-952573a7c8bc",
        "table_number": 36014,
        "reservation_time": "2023-08-09T19:34:51.192Z",
        "created_at": "2023-08-10T08:57:21.410Z",
        "updated_at": "2023-08-09T20:26:53.990Z",
        "guest_id": "user_entity_pk",
        "restaurant_id": "main_entity_pk"
      },
      {
        "id": "76e9b5b5-3584-45a9-9728-c3306b56cce0",
        "table_number": 95938,
        "reservation_time": "2023-08-09T17:48:46.497Z",
        "created_at": "2023-08-10T06:25:36.825Z",
        "updated_at": "2023-08-09T15:53:39.334Z",
        "guest_id": "user_entity_pk",
        "restaurant_id": "main_entity_pk"
      },
      {
        "id": "cf914e00-23cc-49fd-af95-a6a242b8e13c",
        "table_number": 15003,
        "reservation_time": "2023-08-09T23:37:11.775Z",
        "created_at": "2023-08-09T19:04:01.813Z",
        "updated_at": "2023-08-09T14:49:17.397Z",
        "guest_id": "user_entity_pk",
        "restaurant_id": "main_entity_pk"
      }
    ],
    "menu": [
      {
        "id": "7358621e-0b24-48b7-8e17-31fd6f51689a",
        "name": "Grilled Salmon",
        "created_at": "2023-08-09T13:08:56.360Z",
        "updated_at": "2023-08-10T08:54:38.267Z",
        "restaurant_id": "main_entity_pk"
      },
      {
        "id": "820d9bdd-61c8-4ffd-8f91-76fad602eaa6",
        "name": "Margherita Pizza",
        "created_at": "2023-08-09T19:21:56.108Z",
        "updated_at": "2023-08-10T10:36:02.218Z",
        "restaurant_id": "main_entity_pk"
      },
      {
        "id": "b6d02fc5-b83b-4060-b4fa-985458274bc7",
        "name": "Chicken Alfredo Pasta",
        "created_at": "2023-08-09T22:15:18.066Z",
        "updated_at": "2023-08-10T09:32:12.932Z",
        "restaurant_id": "main_entity_pk"
      },
      {
        "id": "c02e9274-5248-4109-ad92-bfec09918966",
        "name": "Beef Burger",
        "created_at": "2023-08-10T02:18:15.243Z",
        "updated_at": "2023-08-09T11:52:17.652Z",
        "restaurant_id": "main_entity_pk"
      },
      {
        "id": "9bfc7857-f7d9-4b30-a9f5-9a77c33bfbdb",
        "name": "Vegetable Stir-Fry",
        "created_at": "2023-08-10T01:57:34.105Z",
        "updated_at": "2023-08-09T11:54:41.725Z",
        "restaurant_id": "main_entity_pk"
      }
    ],
    "roqUser": [
      {
        "reference": "d5f13314-1c58-4c63-a2eb-a8ca12069dd0",
        "email": "Nellie21@yahoo.com",
        "firstName": "Micheal",
        "lastName": "Boyer",
        "active": true,
        "avatarUrl": "https://cloudflare-ipfs.com/ipfs/Qmd3W5DuhgHirLHGVixi6V76LhCkZUz6pnFt5AJBiyvHye/avatar/532.jpg",
        "tenantId": null
      },
      {
        "reference": "a0beb071-1973-4648-b2ca-2648fb11255a",
        "email": "Roosevelt_Feeney@yahoo.com",
        "firstName": "Delpha",
        "lastName": "Sipes",
        "active": true,
        "avatarUrl": "https://cloudflare-ipfs.com/ipfs/Qmd3W5DuhgHirLHGVixi6V76LhCkZUz6pnFt5AJBiyvHye/avatar/1210.jpg",
        "tenantId": null
      },
      {
        "reference": "9904d535-fc5a-4021-be52-b24a163fe428",
        "email": "Jeanette_Vandervort@hotmail.com",
        "firstName": "Nellie",
        "lastName": "Reinger",
        "active": true,
        "avatarUrl": "https://cloudflare-ipfs.com/ipfs/Qmd3W5DuhgHirLHGVixi6V76LhCkZUz6pnFt5AJBiyvHye/avatar/357.jpg",
        "tenantId": null
      },
      {
        "reference": "5d83e424-694d-46aa-8e4d-3de14c0a4597",
        "email": "Zakary12@yahoo.com",
        "firstName": "Aylin",
        "lastName": "Marks",
        "active": true,
        "avatarUrl": "https://cloudflare-ipfs.com/ipfs/Qmd3W5DuhgHirLHGVixi6V76LhCkZUz6pnFt5AJBiyvHye/avatar/1199.jpg",
        "tenantId": null
      },
      {
        "reference": "4e0ab067-6d90-4aeb-90b7-d9de97137b94",
        "email": "Tomas_Kuhlman7@hotmail.com",
        "firstName": "Hanna",
        "lastName": "Morar",
        "active": true,
        "avatarUrl": "https://cloudflare-ipfs.com/ipfs/Qmd3W5DuhgHirLHGVixi6V76LhCkZUz6pnFt5AJBiyvHye/avatar/288.jpg",
        "tenantId": null
      }
    ]
  },
  {
    "reservation": [
      {
        "id": "0c85c784-b090-4fc8-b76d-7797783e4edd",
        "table_number": 81646,
        "reservation_time": "2023-08-09T18:07:05.706Z",
        "created_at": "2023-08-09T14:16:24.321Z",
        "updated_at": "2023-08-09T11:55:55.538Z",
        "guest_id": "user_entity_pk",
        "restaurant_id": "main_entity_pk"
      },
      {
        "id": "c2e49160-f4c8-4533-a754-2abd6bcebc17",
        "table_number": 39161,
        "reservation_time": "2023-08-10T08:22:04.497Z",
        "created_at": "2023-08-09T23:16:06.371Z",
        "updated_at": "2023-08-09T22:49:29.896Z",
        "guest_id": "user_entity_pk",
        "restaurant_id": "main_entity_pk"
      },
      {
        "id": "b5b4ffff-3857-485e-aa9d-a416a8c5fa46",
        "table_number": 72956,
        "reservation_time": "2023-08-10T00:50:32.687Z",
        "created_at": "2023-08-09T15:42:32.157Z",
        "updated_at": "2023-08-09T13:25:20.597Z",
        "guest_id": "user_entity_pk",
        "restaurant_id": "main_entity_pk"
      },
      {
        "id": "ac9cafe9-acf5-48a6-8c04-d184ab431e65",
        "table_number": 82803,
        "reservation_time": "2023-08-09T23:29:34.293Z",
        "created_at": "2023-08-10T06:25:18.198Z",
        "updated_at": "2023-08-10T01:52:08.712Z",
        "guest_id": "user_entity_pk",
        "restaurant_id": "main_entity_pk"
      },
      {
        "id": "359f52c9-2099-4861-b0cc-664834fe77f3",
        "table_number": 45639,
        "reservation_time": "2023-08-10T02:32:30.641Z",
        "created_at": "2023-08-09T12:59:41.809Z",
        "updated_at": "2023-08-09T18:11:54.512Z",
        "guest_id": "user_entity_pk",
        "restaurant_id": "main_entity_pk"
      }
    ],
    "menu": [
      {
        "id": "33c9f304-c599-4366-ba32-193c318c05b5",
        "name": "Breakfast Specials",
        "created_at": "2023-08-10T00:21:53.119Z",
        "updated_at": "2023-08-10T07:08:18.188Z",
        "restaurant_id": "main_entity_pk"
      },
      {
        "id": "75eb5097-c6cc-42c0-9d8d-3bbf732dbf62",
        "name": "Lunch Combos",
        "created_at": "2023-08-09T22:16:40.126Z",
        "updated_at": "2023-08-10T05:31:40.878Z",
        "restaurant_id": "main_entity_pk"
      },
      {
        "id": "6055f8ad-823a-44f5-88e8-c8e26d013e99",
        "name": "Dinner Delights",
        "created_at": "2023-08-09T22:59:10.401Z",
        "updated_at": "2023-08-09T13:26:17.785Z",
        "restaurant_id": "main_entity_pk"
      },
      {
        "id": "e6823d73-d65b-4f41-ac85-a7627be4a308",
        "name": "Vegetarian Options",
        "created_at": "2023-08-09T13:34:57.020Z",
        "updated_at": "2023-08-10T11:18:24.266Z",
        "restaurant_id": "main_entity_pk"
      },
      {
        "id": "dd9883b8-b3ab-4d34-bb94-cc96b5330570",
        "name": "Chef's Recommendations",
        "created_at": "2023-08-10T08:38:43.730Z",
        "updated_at": "2023-08-10T00:37:02.892Z",
        "restaurant_id": "main_entity_pk"
      }
    ],
    "roqUser": [
      {
        "reference": "af215c1a-1502-4c99-ad97-da464d75cc9b",
        "email": "Beau.Kutch@hotmail.com",
        "firstName": "Rod",
        "lastName": "Hermiston",
        "active": true,
        "avatarUrl": "https://cloudflare-ipfs.com/ipfs/Qmd3W5DuhgHirLHGVixi6V76LhCkZUz6pnFt5AJBiyvHye/avatar/54.jpg",
        "tenantId": null
      },
      {
        "reference": "d8926b2d-242c-4058-8f30-59178e701fba",
        "email": "Zackery.Reichel9@yahoo.com",
        "firstName": "Jaylin",
        "lastName": "Nader",
        "active": true,
        "avatarUrl": "https://avatars.githubusercontent.com/u/92905978",
        "tenantId": null
      },
      {
        "reference": "7a4756d1-3dba-4c4c-824a-ad4a980947a3",
        "email": "Gunnar.Casper@gmail.com",
        "firstName": "Maximus",
        "lastName": "Mann",
        "active": true,
        "avatarUrl": "https://cloudflare-ipfs.com/ipfs/Qmd3W5DuhgHirLHGVixi6V76LhCkZUz6pnFt5AJBiyvHye/avatar/581.jpg",
        "tenantId": null
      },
      {
        "reference": "c305cc46-984b-43ff-8e07-4bcc94ad3b3f",
        "email": "Reyes_Herman36@yahoo.com",
        "firstName": "Shea",
        "lastName": "Gottlieb",
        "active": true,
        "avatarUrl": "https://cloudflare-ipfs.com/ipfs/Qmd3W5DuhgHirLHGVixi6V76LhCkZUz6pnFt5AJBiyvHye/avatar/554.jpg",
        "tenantId": null
      },
      {
        "reference": "f6b3a4d5-a655-43a1-9973-620fee1180ad",
        "email": "Eliezer.Mayert@yahoo.com",
        "firstName": "Ayana",
        "lastName": "Bauch",
        "active": true,
        "avatarUrl": "https://avatars.githubusercontent.com/u/53435647",
        "tenantId": null
      }
    ]
  },
  {
    "reservation": [
      {
        "id": "b1d65994-7bcb-4278-9346-601e661102fa",
        "table_number": 998,
        "reservation_time": "2023-08-10T07:50:19.785Z",
        "created_at": "2023-08-09T19:06:29.967Z",
        "updated_at": "2023-08-09T12:23:23.426Z",
        "guest_id": "user_entity_pk",
        "restaurant_id": "main_entity_pk"
      },
      {
        "id": "ef346212-cecb-4fcf-985f-671419321838",
        "table_number": 9133,
        "reservation_time": "2023-08-10T07:37:50.669Z",
        "created_at": "2023-08-09T17:27:20.191Z",
        "updated_at": "2023-08-09T15:54:45.500Z",
        "guest_id": "user_entity_pk",
        "restaurant_id": "main_entity_pk"
      },
      {
        "id": "e487d3a0-197f-44e6-9011-f6536707f0c3",
        "table_number": 70293,
        "reservation_time": "2023-08-09T23:28:57.516Z",
        "created_at": "2023-08-09T23:25:49.299Z",
        "updated_at": "2023-08-10T00:00:19.875Z",
        "guest_id": "user_entity_pk",
        "restaurant_id": "main_entity_pk"
      },
      {
        "id": "d199b696-619e-4f58-ad3d-603e36c46e3a",
        "table_number": 21482,
        "reservation_time": "2023-08-10T06:40:44.311Z",
        "created_at": "2023-08-09T14:49:50.034Z",
        "updated_at": "2023-08-09T16:53:24.960Z",
        "guest_id": "user_entity_pk",
        "restaurant_id": "main_entity_pk"
      },
      {
        "id": "bc33c812-9f01-40c6-9a92-2646f457eaa5",
        "table_number": 22332,
        "reservation_time": "2023-08-09T22:17:00.590Z",
        "created_at": "2023-08-09T19:51:02.540Z",
        "updated_at": "2023-08-09T15:49:01.938Z",
        "guest_id": "user_entity_pk",
        "restaurant_id": "main_entity_pk"
      }
    ],
    "menu": [
      {
        "id": "d364b372-942f-49a8-b274-aeabfba581f9",
        "name": "Breakfast Specials",
        "created_at": "2023-08-09T19:45:51.268Z",
        "updated_at": "2023-08-09T22:28:58.797Z",
        "restaurant_id": "main_entity_pk"
      },
      {
        "id": "731270b5-15f0-4933-bec7-0d1aaa2b658e",
        "name": "Lunch Combos",
        "created_at": "2023-08-10T07:33:35.324Z",
        "updated_at": "2023-08-09T17:06:03.431Z",
        "restaurant_id": "main_entity_pk"
      },
      {
        "id": "059f62de-1c2b-4053-a0ba-4fe886d177ec",
        "name": "Dinner Delights",
        "created_at": "2023-08-10T07:37:55.076Z",
        "updated_at": "2023-08-10T02:41:49.534Z",
        "restaurant_id": "main_entity_pk"
      },
      {
        "id": "656d107d-5963-45de-96a9-481b659a3010",
        "name": "Vegetarian Options",
        "created_at": "2023-08-10T05:29:56.046Z",
        "updated_at": "2023-08-09T11:49:58.053Z",
        "restaurant_id": "main_entity_pk"
      },
      {
        "id": "ea2a78c2-9b4b-4446-a680-9d47e7080d2d",
        "name": "Chef's Recommendations",
        "created_at": "2023-08-09T20:03:21.096Z",
        "updated_at": "2023-08-10T08:26:32.126Z",
        "restaurant_id": "main_entity_pk"
      }
    ],
    "roqUser": [
      {
        "reference": "f42113d3-d6ce-4b6d-a425-410cf25534de",
        "email": "Cierra_Dibbert93@gmail.com",
        "firstName": "Hardy",
        "lastName": "Cole",
        "active": true,
        "avatarUrl": "https://cloudflare-ipfs.com/ipfs/Qmd3W5DuhgHirLHGVixi6V76LhCkZUz6pnFt5AJBiyvHye/avatar/749.jpg",
        "tenantId": null
      },
      {
        "reference": "a507c8f4-5d15-4540-87b2-c5ba808da414",
        "email": "Angus63@hotmail.com",
        "firstName": "Delphine",
        "lastName": "Keeling",
        "active": true,
        "avatarUrl": "https://cloudflare-ipfs.com/ipfs/Qmd3W5DuhgHirLHGVixi6V76LhCkZUz6pnFt5AJBiyvHye/avatar/933.jpg",
        "tenantId": null
      },
      {
        "reference": "8f036b29-e1ec-4834-ab95-5999813ad6f9",
        "email": "Amaya_Bins@gmail.com",
        "firstName": "Janessa",
        "lastName": "Aufderhar",
        "active": true,
        "avatarUrl": "https://cloudflare-ipfs.com/ipfs/Qmd3W5DuhgHirLHGVixi6V76LhCkZUz6pnFt5AJBiyvHye/avatar/209.jpg",
        "tenantId": null
      },
      {
        "reference": "71c1d230-5e53-4c56-a4c6-a53231be4837",
        "email": "Trey.Reilly@yahoo.com",
        "firstName": "Nova",
        "lastName": "Flatley",
        "active": true,
        "avatarUrl": "https://cloudflare-ipfs.com/ipfs/Qmd3W5DuhgHirLHGVixi6V76LhCkZUz6pnFt5AJBiyvHye/avatar/678.jpg",
        "tenantId": null
      },
      {
        "reference": "d89c66b9-c6e9-48c0-a01e-c6e0638d28e2",
        "email": "Elenor.Harvey@hotmail.com",
        "firstName": "Lucy",
        "lastName": "Zboncak",
        "active": true,
        "avatarUrl": "https://cloudflare-ipfs.com/ipfs/Qmd3W5DuhgHirLHGVixi6V76LhCkZUz6pnFt5AJBiyvHye/avatar/519.jpg",
        "tenantId": null
      }
    ]
  },
  {
    "reservation": [
      {
        "id": "562cc229-deed-46dc-9ad7-235e1905fd84",
        "table_number": 83561,
        "reservation_time": "2023-08-09T21:59:04.248Z",
        "created_at": "2023-08-09T23:46:10.122Z",
        "updated_at": "2023-08-09T19:43:08.887Z",
        "guest_id": "user_entity_pk",
        "restaurant_id": "main_entity_pk"
      },
      {
        "id": "2149ab42-70fd-4782-9316-20da09eeb3bf",
        "table_number": 39999,
        "reservation_time": "2023-08-09T16:21:32.099Z",
        "created_at": "2023-08-09T19:22:24.806Z",
        "updated_at": "2023-08-09T15:41:06.437Z",
        "guest_id": "user_entity_pk",
        "restaurant_id": "main_entity_pk"
      },
      {
        "id": "d0841518-413e-4daa-8231-3df8df10ca81",
        "table_number": 62229,
        "reservation_time": "2023-08-10T09:57:53.061Z",
        "created_at": "2023-08-09T17:38:16.181Z",
        "updated_at": "2023-08-09T13:53:44.504Z",
        "guest_id": "user_entity_pk",
        "restaurant_id": "main_entity_pk"
      },
      {
        "id": "f3629b93-352d-4c5a-ac48-bdb5cbbabafe",
        "table_number": 82369,
        "reservation_time": "2023-08-10T10:25:31.776Z",
        "created_at": "2023-08-09T14:34:26.520Z",
        "updated_at": "2023-08-10T11:45:29.210Z",
        "guest_id": "user_entity_pk",
        "restaurant_id": "main_entity_pk"
      },
      {
        "id": "1ada9069-cd52-4a4f-8a3f-480f35ca21e4",
        "table_number": 90295,
        "reservation_time": "2023-08-09T13:02:11.069Z",
        "created_at": "2023-08-09T15:16:55.344Z",
        "updated_at": "2023-08-10T05:39:31.352Z",
        "guest_id": "user_entity_pk",
        "restaurant_id": "main_entity_pk"
      }
    ],
    "menu": [
      {
        "id": "09174bf2-103c-4578-8e95-5db7a6d3faf2",
        "name": "Breakfast Specials",
        "created_at": "2023-08-09T17:53:56.376Z",
        "updated_at": "2023-08-09T12:38:11.472Z",
        "restaurant_id": "main_entity_pk"
      },
      {
        "id": "e36de511-159f-4ed7-a732-4dde1af54a8a",
        "name": "Chef's Recommendations",
        "created_at": "2023-08-09T21:38:42.259Z",
        "updated_at": "2023-08-10T08:22:08.719Z",
        "restaurant_id": "main_entity_pk"
      },
      {
        "id": "edf63275-1f25-4f18-90e1-898f5a79aef0",
        "name": "Vegetarian Delights",
        "created_at": "2023-08-09T15:50:41.758Z",
        "updated_at": "2023-08-09T14:55:22.816Z",
        "restaurant_id": "main_entity_pk"
      },
      {
        "id": "e324ab7d-dae2-4f61-8e2c-67fe4d373bc3",
        "name": "Seafood Extravaganza",
        "created_at": "2023-08-10T09:18:25.010Z",
        "updated_at": "2023-08-10T03:09:23.184Z",
        "restaurant_id": "main_entity_pk"
      },
      {
        "id": "4ab3eba6-0318-4229-959b-83a340095add",
        "name": "Sweet Treats",
        "created_at": "2023-08-09T22:01:25.553Z",
        "updated_at": "2023-08-10T07:27:46.211Z",
        "restaurant_id": "main_entity_pk"
      }
    ],
    "roqUser": [
      {
        "reference": "667c3fec-c0b4-4de2-a0b6-e67911a968cb",
        "email": "Alexandrine30@hotmail.com",
        "firstName": "Rosa",
        "lastName": "DuBuque",
        "active": true,
        "avatarUrl": "https://avatars.githubusercontent.com/u/44303265",
        "tenantId": null
      },
      {
        "reference": "d71135d4-2629-4f8c-a83c-3a11a86d822a",
        "email": "Noble_Parker@gmail.com",
        "firstName": "Leonard",
        "lastName": "Blick",
        "active": true,
        "avatarUrl": "https://cloudflare-ipfs.com/ipfs/Qmd3W5DuhgHirLHGVixi6V76LhCkZUz6pnFt5AJBiyvHye/avatar/980.jpg",
        "tenantId": null
      },
      {
        "reference": "bfc42c5f-26e1-4dbb-b2d1-dddd2a642a53",
        "email": "Marcelo41@hotmail.com",
        "firstName": "Katrina",
        "lastName": "Flatley",
        "active": true,
        "avatarUrl": "https://cloudflare-ipfs.com/ipfs/Qmd3W5DuhgHirLHGVixi6V76LhCkZUz6pnFt5AJBiyvHye/avatar/739.jpg",
        "tenantId": null
      },
      {
        "reference": "b87912e2-27f7-46ba-8474-46d78b81a8fe",
        "email": "Darrel.McCullough@gmail.com",
        "firstName": "Felicity",
        "lastName": "Nienow",
        "active": true,
        "avatarUrl": "https://avatars.githubusercontent.com/u/89796809",
        "tenantId": null
      },
      {
        "reference": "7de78f7e-c9fd-4e10-8512-eacdd18cc08f",
        "email": "Nakia_Brakus97@hotmail.com",
        "firstName": "Gus",
        "lastName": "Schmitt",
        "active": true,
        "avatarUrl": "https://cloudflare-ipfs.com/ipfs/Qmd3W5DuhgHirLHGVixi6V76LhCkZUz6pnFt5AJBiyvHye/avatar/493.jpg",
        "tenantId": null
      }
    ]
  },
  {
    "reservation": [
      {
        "id": "8f4dcf75-1912-4d65-9af5-db52461f3c89",
        "table_number": 98026,
        "reservation_time": "2023-08-09T14:12:20.448Z",
        "created_at": "2023-08-09T17:07:35.940Z",
        "updated_at": "2023-08-09T13:58:40.733Z",
        "guest_id": "user_entity_pk",
        "restaurant_id": "main_entity_pk"
      },
      {
        "id": "e5719758-1b03-4e5d-822e-59dc4d4768e7",
        "table_number": 5357,
        "reservation_time": "2023-08-10T08:25:49.540Z",
        "created_at": "2023-08-09T17:24:43.922Z",
        "updated_at": "2023-08-09T12:18:34.616Z",
        "guest_id": "user_entity_pk",
        "restaurant_id": "main_entity_pk"
      },
      {
        "id": "3b35916b-d1ee-4cfe-8f6e-5c2ca8ab468f",
        "table_number": 93798,
        "reservation_time": "2023-08-10T10:40:16.567Z",
        "created_at": "2023-08-09T22:25:08.504Z",
        "updated_at": "2023-08-09T15:57:35.919Z",
        "guest_id": "user_entity_pk",
        "restaurant_id": "main_entity_pk"
      },
      {
        "id": "97c9aa88-c341-4915-a202-19f77a5ce694",
        "table_number": 38048,
        "reservation_time": "2023-08-10T04:54:08.328Z",
        "created_at": "2023-08-10T08:02:59.831Z",
        "updated_at": "2023-08-10T02:20:39.053Z",
        "guest_id": "user_entity_pk",
        "restaurant_id": "main_entity_pk"
      },
      {
        "id": "3eaae005-2d51-450b-ba23-b799bc78014e",
        "table_number": 47586,
        "reservation_time": "2023-08-10T05:49:19.948Z",
        "created_at": "2023-08-10T04:07:40.170Z",
        "updated_at": "2023-08-10T03:04:36.614Z",
        "guest_id": "user_entity_pk",
        "restaurant_id": "main_entity_pk"
      }
    ],
    "menu": [
      {
        "id": "df0017da-f89f-4be3-b94f-bc6366db8ead",
        "name": "Breakfast Specials",
        "created_at": "2023-08-10T02:57:54.029Z",
        "updated_at": "2023-08-09T11:56:26.186Z",
        "restaurant_id": "main_entity_pk"
      },
      {
        "id": "d04e1a57-4551-453d-ad9e-9d70a8053db1",
        "name": "Lunch Combos",
        "created_at": "2023-08-09T23:40:07.365Z",
        "updated_at": "2023-08-10T01:42:22.569Z",
        "restaurant_id": "main_entity_pk"
      },
      {
        "id": "8e087dd2-3407-476d-9e29-655c4ac32a67",
        "name": "Dinner Entrees",
        "created_at": "2023-08-10T05:22:18.543Z",
        "updated_at": "2023-08-10T00:03:50.158Z",
        "restaurant_id": "main_entity_pk"
      },
      {
        "id": "10bf6807-7ca5-46d0-af52-23e9fb8e6d76",
        "name": "Vegetarian Options",
        "created_at": "2023-08-10T09:35:48.775Z",
        "updated_at": "2023-08-10T03:57:23.648Z",
        "restaurant_id": "main_entity_pk"
      },
      {
        "id": "2bacfcc0-b24d-408b-a089-1f5e56efa6ab",
        "name": "Chef's Recommendations",
        "created_at": "2023-08-09T19:54:16.490Z",
        "updated_at": "2023-08-10T03:16:45.852Z",
        "restaurant_id": "main_entity_pk"
      }
    ],
    "roqUser": [
      {
        "reference": "1f1b7fa5-eeab-4301-918e-517a8aa90e91",
        "email": "Rosina_Muller@hotmail.com",
        "firstName": "Guy",
        "lastName": "Kautzer",
        "active": true,
        "avatarUrl": "https://cloudflare-ipfs.com/ipfs/Qmd3W5DuhgHirLHGVixi6V76LhCkZUz6pnFt5AJBiyvHye/avatar/1154.jpg",
        "tenantId": null
      },
      {
        "reference": "7a4dfdae-488f-4331-a7ec-8cefe1226f75",
        "email": "Arely_Herman99@gmail.com",
        "firstName": "Gayle",
        "lastName": "Conn-Sporer",
        "active": true,
        "avatarUrl": "https://avatars.githubusercontent.com/u/4825675",
        "tenantId": null
      },
      {
        "reference": "556669f3-f695-45db-95c8-845f050ae1e8",
        "email": "Eldon_Cassin84@hotmail.com",
        "firstName": "Malinda",
        "lastName": "Conn",
        "active": true,
        "avatarUrl": "https://avatars.githubusercontent.com/u/97625998",
        "tenantId": null
      },
      {
        "reference": "4ae387aa-53ea-4b6a-abb8-ee9d6f370dcb",
        "email": "Kaylin_Nienow@gmail.com",
        "firstName": "Bridget",
        "lastName": "Zulauf",
        "active": true,
        "avatarUrl": "https://avatars.githubusercontent.com/u/53483331",
        "tenantId": null
      },
      {
        "reference": "3df141fd-dd85-4ead-87f6-f13015f192f3",
        "email": "Leann_Weissnat79@yahoo.com",
        "firstName": "Alvis",
        "lastName": "Wiza",
        "active": true,
        "avatarUrl": "https://avatars.githubusercontent.com/u/88661310",
        "tenantId": null
      }
    ]
  }
]
